LICENSE
MANIFEST.in
README.md
pyproject.toml
setup.py
./pyrgbdev/All/SDK.cpp
./pyrgbdev/Corsair/SDK.cpp
./pyrgbdev/Razer/SDK.cpp
pyrgbdev/__init__.py
pyrgbdev/__init__.pyx
pyrgbdev.egg-info/PKG-INFO
pyrgbdev.egg-info/SOURCES.txt
pyrgbdev.egg-info/dependency_links.txt
pyrgbdev.egg-info/requires.txt
pyrgbdev.egg-info/top_level.txt
pyrgbdev/AbstractSDK/README.md
pyrgbdev/AbstractSDK/SDK.pyx
pyrgbdev/AbstractSDK/__init__.py
pyrgbdev/AbstractSDK/__init__.pyx
pyrgbdev/AbstractSDK/abstractSDK.h
pyrgbdev/AbstractSDK/abstractSDK.pxd
pyrgbdev/All/SDK.cpp
pyrgbdev/All/SDK.pyx
pyrgbdev/All/__init__.py
pyrgbdev/Corsair/Corsair.cpp
pyrgbdev/Corsair/Corsair.h
pyrgbdev/Corsair/Corsair.pxd
pyrgbdev/Corsair/SDK.cpp
pyrgbdev/Corsair/SDK.pyx
pyrgbdev/Corsair/__init__.py
pyrgbdev/Corsair/__init__.pyx
pyrgbdev/Corsair/__pycache__/__init__.cpython-310.pyc
pyrgbdev/Corsair/__pycache__/__init__.cpython-38.pyc
pyrgbdev/Corsair/includes/CUESDK.h
pyrgbdev/Corsair/includes/CUESDKGlobal.h
pyrgbdev/Corsair/includes/CorsairKeyIdEnum.h
pyrgbdev/Corsair/includes/CorsairLedIdEnum.h
pyrgbdev/Corsair/libs/CUESDK.x64_2019.lib
pyrgbdev/Razer/Razer.cpp
pyrgbdev/Razer/Razer.h
pyrgbdev/Razer/Razer.pxd
pyrgbdev/Razer/SDK.cpp
pyrgbdev/Razer/SDK.pyx
pyrgbdev/Razer/__init__.py
pyrgbdev/Razer/__init__.pyx
pyrgbdev/Razer/__pycache__/__init__.cpython-310.pyc
pyrgbdev/Razer/includes/RzChromaSDKDefines.h
pyrgbdev/Razer/includes/RzChromaSDKTypes.h
pyrgbdev/Razer/includes/RzErrors.h
pyrgbdev/__pycache__/__init__.cpython-310.pyc
pyrgbdev/__pycache__/__init__.cpython-38.pyc
pyrgbdev/dllHelper/CUESDK.x64_2019.dll
pyrgbdev/dllHelper/README.md
pyrgbdev/dllHelper/helper.bat