Metadata-Version: 2.1
Name: pyrgbdev
Version: 1.0.5
Summary: A RGB Controlling Library for Python
Home-page: https://github.com/gooday2die/pyrgbdev
Author: Gooday2die
Author-email: edina00@naver.com
License: MIT
Platform: UNKNOWN
Classifier: Environment :: Win32 (MS Windows)
Classifier: License :: OSI Approved :: MIT License
Classifier: Natural Language :: English
Classifier: Operating System :: Microsoft :: Windows
Classifier: Topic :: System :: Hardware
License-File: LICENSE
